odoo/addons/sale_invoice_line_note/README.rst
odoo/addons/sale_invoice_line_note/__init__.py
odoo/addons/sale_invoice_line_note/__manifest__.py
odoo/addons/sale_invoice_line_note/i18n/de.po
odoo/addons/sale_invoice_line_note/i18n/es.po
odoo/addons/sale_invoice_line_note/i18n/nl_NL.po
odoo/addons/sale_invoice_line_note/i18n/sale_invoice_line_note.pot
odoo/addons/sale_invoice_line_note/models/__init__.py
odoo/addons/sale_invoice_line_note/models/sale_order.py
odoo/addons/sale_invoice_line_note/readme/CONTRIBUTORS.rst
odoo/addons/sale_invoice_line_note/readme/DESCRIPTION.rst
odoo/addons/sale_invoice_line_note/readme/ROADMAP.rst
odoo/addons/sale_invoice_line_note/static/description/icon.png
odoo/addons/sale_invoice_line_note/static/description/index.html
odoo/addons/sale_invoice_line_note/tests/__init__.py
odoo/addons/sale_invoice_line_note/tests/test_sale_invoice_line_note.py
odoo/addons/sale_invoice_line_note/wizard/__init__.py
odoo/addons/sale_invoice_line_note/wizard/sale_make_invoice_advance.py
odoo/addons/sale_invoice_line_note/wizard/sale_make_invoice_advance.xml
odoo12_addon_sale_invoice_line_note-12.0.1.0.0.99.dev15.dist-info/METADATA
odoo12_addon_sale_invoice_line_note-12.0.1.0.0.99.dev15.dist-info/WHEEL
odoo12_addon_sale_invoice_line_note-12.0.1.0.0.99.dev15.dist-info/top_level.txt
odoo12_addon_sale_invoice_line_note-12.0.1.0.0.99.dev15.dist-info/RECORD
